fastsaebm/__init__.py
fastsaebm/data_generate.py
fastsaebm/fast_kde.py
fastsaebm/mh.py
fastsaebm/run.py
fastsaebm/utils.py
fastsaebm/viz.py
fastsaebm/data/__init__.py
fastsaebm/data/params.json
fastsaebm/data/samples/10|100_0.csv
fastsaebm/data/samples/5|50_0.csv
fastsaebm/test/gen.py
fastsaebm/test/test.py
fastsaebm-0.0.6.dist-info/LICENSE
fastsaebm-0.0.6.dist-info/METADATA
fastsaebm-0.0.6.dist-info/WHEEL
fastsaebm-0.0.6.dist-info/top_level.txt
fastsaebm-0.0.6.dist-info/RECORD
